adjango/__init__.py
adjango/adecorators.py
adjango/apps.py
adjango/aserializers.py
adjango/conf.py
adjango/decorators.py
adjango/descriptors.py
adjango/fields.py
adjango/handlers.py
adjango/middleware.py
adjango/serializers.py
adjango/tasks.py
adjango/testing.py
adjango/constants/__init__.py
adjango/constants/times.py
adjango/exceptions/__init__.py
adjango/exceptions/base.py
adjango/management/__init__.py
adjango/management/commands/__init__.py
adjango/management/commands/add_paths.py
adjango/management/commands/astartproject.py
adjango/management/commands/astartup.py
adjango/management/commands/autosucreate.py
adjango/management/commands/celerybeat.py
adjango/management/commands/celerypurge.py
adjango/management/commands/celeryworker.py
adjango/management/commands/copy_from_root.py
adjango/management/commands/copy_project.py
adjango/management/commands/deletemigrations.py
adjango/management/commands/dumpdata_to_dir.py
adjango/management/commands/loaddata_from_dir.py
adjango/management/commands/newentities.py
adjango/management/commands/remakemigrations.py
adjango/managers/__init__.py
adjango/managers/base.py
adjango/managers/polymorphic.py
adjango/mixins/__init__.py
adjango/mixins/polymorphic/__init__.py
adjango/mixins/polymorphic/admin.py
adjango/models/__init__.py
adjango/models/base.py
adjango/models/choices.py
adjango/models/mixins.py
adjango/models/polymorphic.py
adjango/querysets/__init__.py
adjango/querysets/base.py
adjango/querysets/polymorphic.py
adjango/services/__init__.py
adjango/services/base.py
adjango/utils/__init__.py
adjango/utils/base.py
adjango/utils/common.py
adjango/utils/crontab.py
adjango/utils/funcs.py
adjango/utils/log.py
adjango/utils/mail.py
adjango/utils/pictures.py
adjango/utils/real_ip_middleware.py
adjango/utils/security_middleware.py
adjango/utils/celery/__init__.py
adjango/utils/celery/app.py
adjango/utils/celery/tasker.py
adjango-0.8.3.dist-info/licenses/LICENSE
adjango-0.8.3.dist-info/METADATA
adjango-0.8.3.dist-info/WHEEL
adjango-0.8.3.dist-info/top_level.txt
adjango-0.8.3.dist-info/RECORD
