Metadata-Version: 2.4
Name: adjango
Version: 0.8.3
Summary: A library with many features for interacting with Django
Home-page: https://github.com/Artasov/adjango
Author: xlartas
Author-email: ivanhvalevskey@gmail.com
Project-URL: Source, https://github.com/Artasov/adjango
Project-URL: Tracker, https://github.com/Artasov/adjango/issues
Keywords: adjango django utils funcs features async managers services
Classifier: Framework :: Django
Classifier: Framework :: Django :: 4.2
Classifier: Framework :: Django :: 5
Classifier: Framework :: Django :: 5.1
Classifier: Framework :: Django :: 5.2
Classifier: Programming Language :: Python :: 3.12
Classifier: Operating System :: OS Independent
Classifier: License :: OSI Approved :: MIT License
Classifier: Intended Audience :: Developers
Classifier: Topic :: Software Development :: Libraries :: Application Frameworks
Requires-Python: >=3.12
License-File: LICENSE
Requires-Dist: Django<5.3,>=4.0
Requires-Dist: pyperclip>=1.8.0
Requires-Dist: aiohttp>=3.8.0
Requires-Dist: celery>=5.0.0
Provides-Extra: images
Requires-Dist: Pillow>=9.0.0; extra == "images"
Dynamic: author
Dynamic: author-email
Dynamic: classifier
Dynamic: description
Dynamic: description-content-type
Dynamic: home-page
Dynamic: keywords
Dynamic: license-file
Dynamic: project-url
Dynamic: provides-extra
Dynamic: requires-dist
Dynamic: requires-python
Dynamic: summary
